[
      {
      "name": "Agricultural Business Supplies & Services",
      "id": "34"
   },
      {
      "name": "Apparel",
      "id": "12"
   },
      {
      "name": "Auto Care & Services",
      "id": "43"
   },
      {
      "name": "Automotive business Parts and Supplies",
      "id": "47"
   },
      {
      "name": "Baby, Kids and Toys",
      "id": "11"
   },
      {
      "name": "Books, Music & DVDs",
      "id": "5"
   },
      {
      "name": "Business Products & Services",
      "id": "1400004"
   },
      {
      "name": "Computers",
      "id": "6"
   },
      {
      "name": "Consumer Products & Services",
      "id": "1400002"
   },
      {
      "name": "Contractor",
      "id": "37"
   },
      {
      "name": "Department Store",
      "id": "19"
   },
      {
      "name": "Electronics",
      "id": "14"
   },
      {
      "name": "Fashion & Services",
      "id": "38"
   },
      {
      "name": "Fashion and Accessories",
      "id": "18"
   },
      {
      "name": "Financial & Insurance Services",
      "id": "44"
   },
      {
      "name": "Flowers & Gifts",
      "id": "3"
   },
      {
      "name": "General",
      "id": "32"
   },
      {
      "name": "Grocery & Drugstore & Beverage",
      "id": "36"
   },
      {
      "name": "Health & Beauty",
      "id": "10"
   },
      {
      "name": "Home & Outdoors",
      "id": "4"
   },
      {
      "name": "Home Improvements",
      "id": "41"
   },
      {
      "name": "Household Goods & Services",
      "id": "42"
   },
      {
      "name": "Jewellery & Watches",
      "id": "16"
   },
      {
      "name": "Magazines",
      "id": "35"
   },
      {
      "name": "Moving Services",
      "id": "46"
   },
      {
      "name": "New & Featured Sponsors",
      "id": "1400008"
   },
      {
      "name": "Office Products",
      "id": "9"
   },
      {
      "name": "Pet Supplies",
      "id": "45"
   },
      {
      "name": "Sports and Outdoors",
      "id": "13"
   },
      {
      "name": "Travel & Accommodations",
      "id": "15"
   },
      {
      "name": "Women's Apparel",
      "id": "7"
   }
]